annchih/__init__.py
annchih/core.py
annchih-0.1.1.dist-info/METADATA
annchih-0.1.1.dist-info/WHEEL
annchih-0.1.1.dist-info/top_level.txt
annchih-0.1.1.dist-info/RECORD
