Metadata-Version: 2.4
Name: Annchih
Version: 0.1.1
Summary: Утилита для извлечения ключевых слов и краткого резюме из текста
Home-page: https://github.com/yourusername/Annchih
Author: Annchih
Author-email: you@example.com
Classifier: Programming Language :: Python :: 3
Classifier: License :: OSI Approved :: MIT License
Dynamic: author
Dynamic: author-email
Dynamic: classifier
Dynamic: description
Dynamic: description-content-type
Dynamic: home-page
Dynamic: summary
